popcorntime/__init__.py
popcorntime/popcorntime.py
popcorntime/wrapers.py
popcorn_time-1.0.2.dist-info/LICENSE
popcorn_time-1.0.2.dist-info/METADATA
popcorn_time-1.0.2.dist-info/WHEEL
popcorn_time-1.0.2.dist-info/top_level.txt
popcorn_time-1.0.2.dist-info/RECORD
