Metadata-Version: 2.1
Name: popcorn-time
Version: 1.0.2
Summary: Interact with the Popcorn Time API with python
Home-page: https://github.com/DEADSEC-SECURITY/popcorn-time-api
Author: DeadSec-Security
Author-email: amng835@gmail.com
License: MIT
Keywords: popcorn,popcorntime,popcorn-time,popcorn api,popcorntimeapi,popcorntime-api,popcorn-time-api
Requires-Python: >=3.7
License-File: LICENSE
Requires-Dist: requests (==2.27.1)
